spacecutter/__init__.py
spacecutter/callbacks.py
spacecutter/losses.py
spacecutter/models.py
spacecutter-0.2.1.dist-info/LICENSE
spacecutter-0.2.1.dist-info/METADATA
spacecutter-0.2.1.dist-info/WHEEL
spacecutter-0.2.1.dist-info/top_level.txt
spacecutter-0.2.1.dist-info/RECORD
