Metadata-Version: 2.1
Name: spacecutter
Version: 0.2.1
Summary: Ordinal regression models in PyTorch
Home-page: https://github.com/EthanRosenthal/spacecutter
Author: Ethan Rosenthal
Author-email: ethanrosenthal@gmail.com
License: UNKNOWN
Keywords: machine learning statistics
Platform: UNKNOWN
Classifier: Development Status :: 3 - Alpha
Classifier: Intended Audience :: Developers
Classifier: Topic :: Scientific/Engineering :: Information Analysis
Classifier: License :: OSI Approved :: MIT License
Classifier: Programming Language :: Python :: 3
License-File: LICENSE
Requires-Dist: numpy
Requires-Dist: torch (>=1.1.0)
Provides-Extra: test
Requires-Dist: pytest ; extra == 'test'
Requires-Dist: pytest-cov ; extra == 'test'
Requires-Dist: skorch (>=0.7.0) ; extra == 'test'
